handwriting_visualizations/AdvancedPlots.py
handwriting_visualizations/Configs.py
handwriting_visualizations/SimplePlots.py
handwriting_visualizations/__init__.py
handwriting_visualizations/handwriting_visualisations.py
handwriting_visualizations/visualization_tools.py
handwriting_visualizations-0.3.0.dist-info/METADATA
handwriting_visualizations-0.3.0.dist-info/WHEEL
handwriting_visualizations-0.3.0.dist-info/RECORD
